setup.py
hyh_probability/Binomialdistribution.py
hyh_probability/Gaussiandistribution.py
hyh_probability/Generaldistribution.py
hyh_probability/__init__.py
hyh_probability.egg-info/PKG-INFO
hyh_probability.egg-info/SOURCES.txt
hyh_probability.egg-info/dependency_links.txt
hyh_probability.egg-info/not-zip-safe
hyh_probability.egg-info/top_level.txt