Metadata-Version: 1.0
Name: hyh-probability
Version: 0.1
Summary: Gaussian , Binomial distributions 
Home-page: UNKNOWN
Author: YehangHan
Author-email: test@gmail.com
License: UNKNOWN
Platform: UNKNOWN
